WaldurSA_TUI_package/__init__.py
WaldurSA_TUI_package/configured_offerings.py
WaldurSA_TUI_package/dashboard.py
WaldurSA_TUI_package/error.py
WaldurSA_TUI_package/logs.py
WaldurSA_TUI_package/main.py
WaldurSA_TUI_package/main.tcss
WaldurSA_TUI_package/quit.py
waldursa_tui_package-0.1.9.dist-info/LICENSE
waldursa_tui_package-0.1.9.dist-info/METADATA
waldursa_tui_package-0.1.9.dist-info/WHEEL
waldursa_tui_package-0.1.9.dist-info/entry_points.txt
waldursa_tui_package-0.1.9.dist-info/RECORD
