Metadata-Version: 2.1
Name: WaldurSA_TUI_package
Version: 0.1.9
Summary: Terminal user interface (TUI) for Waldur Site Agent.
License: MIT
Author: Oliver Jõgar
Author-email: oliver.jogar@ut.ee
Requires-Python: >=3.9,<4.0
Classifier: License :: OSI Approved :: MIT License
Classifier: Programming Language :: Python :: 3
Classifier: Programming Language :: Python :: 3.9
Classifier: Programming Language :: Python :: 3.10
Classifier: Programming Language :: Python :: 3.11
Classifier: Programming Language :: Python :: 3.12
Classifier: Programming Language :: Python :: 3.13
Requires-Dist: textual (>=0.82.0,<0.83.0)
Requires-Dist: textual-datepicker (>=0.2.4,<0.3.0)
Requires-Dist: textual-plotext (>=0.2.1,<0.3.0)
